CMakeLists.txt
MANIFEST.in
README.md
setup.py
src/circle_vis.cpp
src/shader_s.cpp
src/shader_s.hpp
third_party/KHR/khrplatform.h
third_party/cmake/FindASSIMP.cmake
third_party/cmake/FindGLFW3.cmake
third_party/cmake/FindGLM.cmake
third_party/glad/glad.c
third_party/glad/glad.h
third_party/glm/CMakeLists.txt
third_party/glm/common.hpp
third_party/glm/exponential.hpp
third_party/glm/ext.hpp
third_party/glm/fwd.hpp
third_party/glm/geometric.hpp
third_party/glm/glm.hpp
third_party/glm/integer.hpp
third_party/glm/mat2x2.hpp
third_party/glm/mat2x3.hpp
third_party/glm/mat2x4.hpp
third_party/glm/mat3x2.hpp
third_party/glm/mat3x3.hpp
third_party/glm/mat3x4.hpp
third_party/glm/mat4x2.hpp
third_party/glm/mat4x3.hpp
third_party/glm/mat4x4.hpp
third_party/glm/matrix.hpp
third_party/glm/packing.hpp
third_party/glm/trigonometric.hpp
third_party/glm/vec2.hpp
third_party/glm/vec3.hpp
third_party/glm/vec4.hpp
third_party/glm/vector_relational.hpp
third_party/glm/detail/_features.hpp
third_party/glm/detail/_fixes.hpp
third_party/glm/detail/_noise.hpp
third_party/glm/detail/_swizzle.hpp
third_party/glm/detail/_swizzle_func.hpp
third_party/glm/detail/_vectorize.hpp
third_party/glm/detail/compute_common.hpp
third_party/glm/detail/compute_vector_relational.hpp
third_party/glm/detail/func_common.inl
third_party/glm/detail/func_common_simd.inl
third_party/glm/detail/func_exponential.inl
third_party/glm/detail/func_exponential_simd.inl
third_party/glm/detail/func_geometric.inl
third_party/glm/detail/func_geometric_simd.inl
third_party/glm/detail/func_integer.inl
third_party/glm/detail/func_integer_simd.inl
third_party/glm/detail/func_matrix.inl
third_party/glm/detail/func_matrix_simd.inl
third_party/glm/detail/func_packing.inl
third_party/glm/detail/func_packing_simd.inl
third_party/glm/detail/func_trigonometric.inl
third_party/glm/detail/func_trigonometric_simd.inl
third_party/glm/detail/func_vector_relational.inl
third_party/glm/detail/func_vector_relational_simd.inl
vdynamics.egg-info/PKG-INFO
vdynamics.egg-info/SOURCES.txt
vdynamics.egg-info/dependency_links.txt
vdynamics.egg-info/not-zip-safe
vdynamics.egg-info/requires.txt
vdynamics.egg-info/top_level.txt
