Metadata-Version: 2.1
Name: vdynamics
Version: 0.1
Summary: Realtime visualization of 2D and 3D dynamics of a large number of objects
Home-page: https://github.com/johnaparker/vdynamics
Author: John Parker
Author-email: john7494@gmail.com
License: MIT
Platform: UNKNOWN
